README.md
pyproject.toml
setup.cfg
titrate/__init__.py
titrate/conftest.py
titrate/datasets.py
titrate/plotting.py
titrate/statistics.py
titrate/upperlimits.py
titrate/utils.py
titrate/validation.py
titrate.egg-info/PKG-INFO
titrate.egg-info/SOURCES.txt
titrate.egg-info/dependency_links.txt
titrate.egg-info/not-zip-safe
titrate.egg-info/requires.txt
titrate.egg-info/top_level.txt