Metadata-Version: 2.2
Name: titrate
Version: 0.5.1
Summary: asympTotic lIkelihood Tests for daRk mAtTer sEarch
Home-page: https://github.com/StFroese/TITRATE
Author: Stefan Fröse
Author-email: stefan.froese@tu-dortmund.de
License: BSD-3-Clause
Classifier: Intended Audience :: Science/Research
Classifier: License :: OSI Approved :: BSD License
Classifier: Operating System :: OS Independent
Classifier: Programming Language :: Python :: 3
Classifier: Programming Language :: Python :: 3.9
Classifier: Programming Language :: Python :: 3.10
Classifier: Programming Language :: Python :: 3.11
Classifier: Topic :: Scientific/Engineering :: Astronomy
Requires-Python: >=3.9
Requires-Dist: numpy
Requires-Dist: scipy
Requires-Dist: matplotlib
Requires-Dist: gammapy==1.2
Requires-Dist: astropy<6.0
Requires-Dist: h5py
Provides-Extra: tests
Requires-Dist: pytest; extra == "tests"
